README.md
setup.py
bin/etl2pcap
bin/etl2xml
etl/__init__.py
etl/dtyp.py
etl/error.py
etl/etl.py
etl/event.py
etl/perf.py
etl/system.py
etl/trace.py
etl/utils.py
etl/wintrace.py
etl/wmi.py
etl/parsers/__init__.py
etl/parsers/tracelogging.py
etl/parsers/etw/AESMService.py
etl/parsers/etw/Application_Addon_Event_Provider.py
etl/parsers/etw/Application_Popup.py
etl/parsers/etw/DptfAcpiEtwProvider.py
etl/parsers/etw/Error_Instrument.py
etl/parsers/etw/HidEventFilter.py
etl/parsers/etw/Intel_SST_BUS.py
etl/parsers/etw/Intel_SST_OED.py
etl/parsers/etw/Intel_Thunderbolt_App.py
etl/parsers/etw/Intel_Thunderbolt_Bus.py
etl/parsers/etw/Intel_Thunderbolt_Service.py
etl/parsers/etw/Intel_iaLPSS2_GPIO2.py
etl/parsers/etw/Intel_iaLPSS2_I2C.py
etl/parsers/etw/Intel_iaLPSS_GPIO.py
etl/parsers/etw/Intel_iaLPSS_I2C.py
etl/parsers/etw/LsaSrv.py
etl/parsers/etw/Microsoft_Antimalware_AMFilter.py
etl/parsers/etw/Microsoft_Antimalware_Protection.py
etl/parsers/etw/Microsoft_Antimalware_RTP.py
etl/parsers/etw/Microsoft_Antimalware_Scan_Interface.py
etl/parsers/etw/Microsoft_Antimalware_Service.py
etl/parsers/etw/Microsoft_AppV_Client.py
etl/parsers/etw/Microsoft_AppV_Client_StreamingUX.py
etl/parsers/etw/Microsoft_AppV_ServiceLog.py
etl/parsers/etw/Microsoft_AppV_SharedPerformance.py
etl/parsers/etw/Microsoft_Client_Licensing_Platform.py
etl/parsers/etw/Microsoft_Gaming_Services.py
etl/parsers/etw/Microsoft_IE.py
etl/parsers/etw/Microsoft_IEFRAME.py
etl/parsers/etw/Microsoft_IE_JSDumpHeap.py
etl/parsers/etw/Microsoft_JScript.py
etl/parsers/etw/Microsoft_Office_Events.py
etl/parsers/etw/Microsoft_Office_Word.py
etl/parsers/etw/Microsoft_Office_Word2.py
etl/parsers/etw/Microsoft_Office_Word3.py
etl/parsers/etw/Microsoft_OneCore_OnlineSetup.py
etl/parsers/etw/Microsoft_Pef_WFP_MessageProvider.py
etl/parsers/etw/Microsoft_Pef_WebProxy.py
etl/parsers/etw/Microsoft_PerfTrack_IEFRAME.py
etl/parsers/etw/Microsoft_PerfTrack_MSHTML.py
etl/parsers/etw/Microsoft_User_Experience_Virtualization_Admin.py
etl_parser.egg-info/PKG-INFO
etl_parser.egg-info/SOURCES.txt
etl_parser.egg-info/dependency_links.txt
etl_parser.egg-info/requires.txt
etl_parser.egg-info/top_level.txt