Metadata-Version: 1.2
Name: etl-parser
Version: 1.0.0
Summary: Event Trace Log file parser in pure Python
Home-page: UNKNOWN
Author: Airbus CERT
Author-email: cert@airbus.com
License: UNKNOWN
Platform: UNKNOWN
Classifier: Programming Language :: Python
Classifier: Programming Language :: Python :: 3
Classifier: Programming Language :: Python :: 3 :: Only
Classifier: Environment :: Console
Classifier: Operating System :: OS Independent
Classifier: License :: OSI Approved :: Apache Software License
Classifier: Topic :: Utilities
Classifier: Intended Audience :: Information Technology
Requires-Python: >=3.6
